odoo/addons/mail_template_subscribe/LICENSE
odoo/addons/mail_template_subscribe/README.rst
odoo/addons/mail_template_subscribe/__init__.py
odoo/addons/mail_template_subscribe/__manifest__.py
odoo/addons/mail_template_subscribe/images/screen.png
odoo/addons/mail_template_subscribe/models/__init__.py
odoo/addons/mail_template_subscribe/models/mail_template.py
odoo/addons/mail_template_subscribe/static/description/icon.png
odoo/addons/mail_template_subscribe/static/description/index.html
odoo/addons/mail_template_subscribe/tests/TEST_INSTRUCTIONS.rst
odoo/addons/mail_template_subscribe/views/mail_template_views.xml
odoo/addons/mail_template_subscribe/wizards/__init__.py
odoo/addons/mail_template_subscribe/wizards/mail_compose_message.py
odoo_addon_mail_template_subscribe-18.0.1.0.0.dist-info/METADATA
odoo_addon_mail_template_subscribe-18.0.1.0.0.dist-info/WHEEL
odoo_addon_mail_template_subscribe-18.0.1.0.0.dist-info/top_level.txt
odoo_addon_mail_template_subscribe-18.0.1.0.0.dist-info/RECORD
